web_fragments/__init__.py
web_fragments/apps.py
web_fragments/fragment.py
web_fragments/views.py
web_fragments/examples/__init__.py
web_fragments/examples/urls.py
web_fragments/examples/views.py
web_fragments/templates/web_fragments/standalone_fragment.html
web_fragments/test_utils/__init__.py
web_fragments/tests/test_fragment.py
web_fragments/tests/test_views.py
web_fragments-3.1.0.dist-info/licenses/AUTHORS
web_fragments-3.1.0.dist-info/licenses/LICENSE.txt
web_fragments-3.1.0.dist-info/METADATA
web_fragments-3.1.0.dist-info/WHEEL
web_fragments-3.1.0.dist-info/top_level.txt
web_fragments-3.1.0.dist-info/RECORD
